sixgill/__init__.py
sixgill/sixgill_actionable_alert_client.py
sixgill/sixgill_alert_client.py
sixgill/sixgill_base_client.py
sixgill/sixgill_constants.py
sixgill/sixgill_enrich_client.py
sixgill/sixgill_exceptions.py
sixgill/sixgill_feed_client.py
sixgill/sixgill_intel_items_client.py
sixgill/sixgill_organization_assets_client.py
sixgill/sixgill_reports_client.py
sixgill/sixgill_unfiltered_enrich_client.py
sixgill/sixgill_utils.py
sixgill/sixgill_request_classes/__init__.py
sixgill/sixgill_request_classes/sixgill_actionable_alert_content_request.py
sixgill/sixgill_request_classes/sixgill_actionable_alert_delete_request.py
sixgill/sixgill_request_classes/sixgill_actionable_alert_patch_request.py
sixgill/sixgill_request_classes/sixgill_actionable_alerts_request.py
sixgill/sixgill_request_classes/sixgill_alerts_digested_request.py
sixgill/sixgill_request_classes/sixgill_alerts_request.py
sixgill/sixgill_request_classes/sixgill_auth_request.py
sixgill/sixgill_request_classes/sixgill_base_post_auth_request.py
sixgill/sixgill_request_classes/sixgill_base_request.py
sixgill/sixgill_request_classes/sixgill_dve_enrich_request.py
sixgill/sixgill_request_classes/sixgill_dve_remediation_request.py
sixgill/sixgill_request_classes/sixgill_feed_digested_request.py
sixgill/sixgill_request_classes/sixgill_feed_request.py
sixgill/sixgill_request_classes/sixgill_field_enrich_request.py
sixgill/sixgill_request_classes/sixgill_intel_items_get_request.py
sixgill/sixgill_request_classes/sixgill_intel_items_post_request.py
sixgill/sixgill_request_classes/sixgill_ioc_enrich_request.py
sixgill/sixgill_request_classes/sixgill_next_batch_intel_items_request.py
sixgill/sixgill_request_classes/sixgill_organization_assets_get_request.py
sixgill/sixgill_request_classes/sixgill_organization_assets_post_request.py
sixgill/sixgill_request_classes/sixgill_organization_assets_put_request.py
sixgill/sixgill_request_classes/sixgill_report_get_html_request.py
sixgill_clients-0.2.27.dist-info/LICENSE
sixgill_clients-0.2.27.dist-info/METADATA
sixgill_clients-0.2.27.dist-info/WHEEL
sixgill_clients-0.2.27.dist-info/top_level.txt
sixgill_clients-0.2.27.dist-info/RECORD
